wavToText/__init__.py
wavToText/wav_to_text.py
wavToText-0.0.4.dist-info/LICENCE
wavToText-0.0.4.dist-info/METADATA
wavToText-0.0.4.dist-info/WHEEL
wavToText-0.0.4.dist-info/top_level.txt
wavToText-0.0.4.dist-info/RECORD
