Metadata-Version: 2.1
Name: wavToText
Version: 0.0.4
Summary: Conevrting english wav audio into text.
Home-page: UNKNOWN
Author: LAKHAL Badr
Author-email: lakhalbadr2@gmail.com
License: UNKNOWN
Platform: UNKNOWN
Requires-Python: == 3.9.10
License-File: LICENCE
Requires-Dist: deepspeech==0.9.3
Requires-Dist: numpy==1.26.0
Requires-Dist: scipy==1.13.1
